odoo/addons/base_tier_validation_check_budget/README.rst
odoo/addons/base_tier_validation_check_budget/__init__.py
odoo/addons/base_tier_validation_check_budget/__manifest__.py
odoo/addons/base_tier_validation_check_budget/models/__init__.py
odoo/addons/base_tier_validation_check_budget/models/tier_definition.py
odoo/addons/base_tier_validation_check_budget/models/tier_review.py
odoo/addons/base_tier_validation_check_budget/models/tier_validation.py
odoo/addons/base_tier_validation_check_budget/readme/CONFIGURE.md
odoo/addons/base_tier_validation_check_budget/readme/CONTRIBUTORS.md
odoo/addons/base_tier_validation_check_budget/readme/DESCRIPTION.md
odoo/addons/base_tier_validation_check_budget/static/description/icon.png
odoo/addons/base_tier_validation_check_budget/static/description/index.html
odoo/addons/base_tier_validation_check_budget/tests/__init__.py
odoo/addons/base_tier_validation_check_budget/tests/test_tier_validation_check_budget.py
odoo/addons/base_tier_validation_check_budget/tests/tier_validation_tester.py
odoo/addons/base_tier_validation_check_budget/views/tier_definition_view.xml
odoo_addon_base_tier_validation_check_budget-18.0.1.0.0.1.dist-info/METADATA
odoo_addon_base_tier_validation_check_budget-18.0.1.0.0.1.dist-info/WHEEL
odoo_addon_base_tier_validation_check_budget-18.0.1.0.0.1.dist-info/top_level.txt
odoo_addon_base_tier_validation_check_budget-18.0.1.0.0.1.dist-info/RECORD
