Metadata-Version: 2.1
Name: odoo-addon-base_tier_validation_check_budget
Version: 18.0.1.0.0.1
Requires-Python: >=3.10
Requires-Dist: odoo-addon-base_tier_validation==18.0.*
Requires-Dist: odoo-addon-budget_control==18.0.*
Requires-Dist: odoo==18.0.*
Summary: Add option to check budget when a tier is validated
Home-page: https://github.com/ecosoft-odoo/budgeting
License: AGPL-3
Author: Ecosoft, Odoo Community Association (OCA)
Author-email: support@odoo-community.org
Classifier: Programming Language :: Python
Classifier: Framework :: Odoo
Classifier: Framework :: Odoo :: 18.0
Classifier: License :: OSI Approved :: GNU Affero General Public License v3
Classifier: Development Status :: 3 - Alpha
